{
	"isVehicle": false,
	"isCleaner": false,
	"isMiner": false,
	"isModul": false,
	"isHatchery": false,
	"isHatcheryModul": false,
	"buildingPath": "",
	"path": "/Game/FactoryGame/Resource/RawResources/Stone/Desc_Stone.Desc_Stone_C",
	"name": "[OLD] Rubyte Ore",
	"consumed": [],
	"produced": [
		{
			"isRecipe": true,
			"type": 0,
			"buildingRecipe": false,
			"productionElement": "/PneumaticFrackingMachine/Recipe_FuckOilToOil_3.Recipe_FuckOilToOil_3_C",
			"wasteProducer": "",
			"input": [
				{
					"item": "/PneumaticFrackingMachine/Desc_AeratedOil.Desc_AeratedOil_C",
					"time": 2,
					"amount": 20000
				},
				{
					"item": "/Game/FactoryGame/Resource/RawResources/Stone/Desc_Stone.Desc_Stone_C",
					"time": 2,
					"amount": 1
				}
			],
			"output": [
				{
					"item": "/Game/FactoryGame/Resource/RawResources/CrudeOil/Desc_LiquidOil.Desc_LiquidOil_C",
					"time": 2,
					"amount": 20000
				}
			],
			"schematics": []
		}
	],
	"dataType": "informations"
}