{
	"path": "/Game/FactoryGame/Resource/Equipment/GolfCart/Desc_GolfCart.Desc_GolfCart_C",
	"name": "Factory Cart™",
	"description": "The one and only FICSIT Factory Cart™\r\nNow with special - FICSIT Foundation only - Grip Wheels, for an even smoother and faster factory floor experience!",
	"gasColor": "00000000",
	"fluidColor": "00000000",
	"canBeSink": true,
	"sinkPoints": 1552,
	"radio": 0,
	"radioActive": false,
	"descriptorType": 2,
	"canDelete": true,
	"energyValue": 0,
	"form": 1,
	"stackSize": 1,
	"schematics": [
		"/SatisfactoryPlus/Content/SchematicManager/Sink/Vanilla/ResourceSink_FactoryCart.ResourceSink_FactoryCart_C",
		"/Game/FactoryGame/Schematics/ResourceSink/ResourceSink_FactoryCart.ResourceSink_FactoryCart_C"
	],
	"itemTypeInformation":
	{
		"type": "normal"
	},
	"image": "/Game/FactoryGame/Equipment/GolfCart/UI/IconDesc_GolfCart_256.IconDesc_GolfCart_256",
	"category": "Tools",
	"subCategory": "",
	"dataType": "itemDescriptor"
}