{
	"path": "/Game/FactoryGame/Resource/Equipment/GolfCart/Desc_GolfCartGold.Desc_GolfCartGold_C",
	"name": "Golden Factory Cart™",
	"description": "The one and only Golden FICSIT Factory Cart™\r\n\r\nYou have now officially ascended. \r\nGo forth now, Master of Spaghetti, God of the Factory, Sinker of Cups, Employee of the Planet... travel in STYLE!",
	"gasColor": "00000000",
	"fluidColor": "00000000",
	"canBeSink": true,
	"sinkPoints": 1852,
	"radio": 0,
	"radioActive": false,
	"descriptorType": 2,
	"canDelete": true,
	"energyValue": 0,
	"form": 1,
	"stackSize": 1,
	"schematics": [
		"/SatisfactoryPlus/Content/SchematicManager/Sink/Vanilla/ResourceSink_GoldenCart.ResourceSink_GoldenCart_C"
	],
	"usedInSchematics": [],
	"itemTypeInformation":
	{
		"type": "normal"
	},
	"image": "/Game/FactoryGame/Equipment/GolfCart/UI/IconDesc_GolfCartGold_256.IconDesc_GolfCartGold_256",
	"category": "Tools",
	"subCategory": "",
	"dataType": "itemDescriptor"
}